hello_world/__init__.py
hello_world/hello_world.py
aws_jsiisamples.jsii_native_python-1.6.0.dist-info/LICENSE
aws_jsiisamples.jsii_native_python-1.6.0.dist-info/METADATA
aws_jsiisamples.jsii_native_python-1.6.0.dist-info/WHEEL
aws_jsiisamples.jsii_native_python-1.6.0.dist-info/top_level.txt
aws_jsiisamples.jsii_native_python-1.6.0.dist-info/RECORD
