Metadata-Version: 2.1
Name: aws-jsiisamples.jsii-native-python
Version: 1.6.0
Summary: A simple Python library to benchmark against a jsii module with similar, simple logic.
Home-page: https://github.com/aws-samples/jsii-native-python
Author: Hari Pachuveetil
Author-email: pachuvee@amazon.com
License: MIT
Download-URL: https://pypi.org/project/jsii-native-python/
Keywords: jsii,python,java,dotnet,typescript,aws
Platform: UNKNOWN
